fetch_security_patches_and_kernel/__init__.py
fetch_security_patches_and_kernel/cmd.py
fetch_linux_security_patches_and_kernel-1.0.3.dist-info/AUTHORS
fetch_linux_security_patches_and_kernel-1.0.3.dist-info/LICENSE
fetch_linux_security_patches_and_kernel-1.0.3.dist-info/METADATA
fetch_linux_security_patches_and_kernel-1.0.3.dist-info/WHEEL
fetch_linux_security_patches_and_kernel-1.0.3.dist-info/entry_points.txt
fetch_linux_security_patches_and_kernel-1.0.3.dist-info/pbr.json
fetch_linux_security_patches_and_kernel-1.0.3.dist-info/top_level.txt
fetch_linux_security_patches_and_kernel-1.0.3.dist-info/RECORD
