Metadata-Version: 2.2
Name: fetch-linux-security-patches-and-kernel
Version: 1.0.3
Summary: Download the latest linux-hardened or unofficial grsecurity 4.9 patch and the matching linux kernel version.
License: MIT
Platform: any
Classifier: Development Status :: 4 - Beta
Classifier: Environment :: Console
Classifier: Intended Audience :: Developers
Classifier: Operating System :: OS Independent
Classifier: Programming Language :: Python
Classifier: Programming Language :: Python :: 3
Classifier: Programming Language :: Python :: 3.4
Classifier: Programming Language :: Python :: 3.5
Classifier: License :: OSI Approved :: MIT License
License-File: LICENSE
License-File: AUTHORS
Requires-Dist: requests<3.0.0,>=2.7.0
Requires-Dist: requests-futures==0.9.7
Requires-Dist: certifi
Dynamic: classifier
Dynamic: license
Dynamic: platform
Dynamic: requires-dist
Dynamic: summary
